convect/__init__.py
convect/command_line.py
convect/helpers.py
convect/sdk.py
convect/tests/__init__.py
convect/tests/test_command_line.py
convect/tests/test_helpers.py
convect/tests/test_sdk.py
convect-0.0.1.post13.dist-info/LICENSE
convect-0.0.1.post13.dist-info/METADATA
convect-0.0.1.post13.dist-info/WHEEL
convect-0.0.1.post13.dist-info/entry_points.txt
convect-0.0.1.post13.dist-info/top_level.txt
convect-0.0.1.post13.dist-info/RECORD
