Metadata-Version: 2.1
Name: convect
Version: 0.0.1.post13
Summary: SDK for Convect
Home-page: https://github.com/convect-ml/convect
Author: Sameeran Kunche
Author-email: sameeran@convect.ml
License: UNKNOWN
Project-URL: Bug Tracker, https://github.com/convect-ml/convect/issues
Platform: UNKNOWN
Classifier: Programming Language :: Python :: 3
Classifier: License :: OSI Approved :: Apache Software License
Classifier: Operating System :: OS Independent
Requires-Python: >=3.7.0
License-File: LICENSE
Requires-Dist: dill
Requires-Dist: requests
Requires-Dist: notebook
Requires-Dist: ipykernel
Requires-Dist: jupyter-contrib-nbextensions
Requires-Dist: nbconvert (<6)
Requires-Dist: pandas (==1.2.4)
Requires-Dist: scikit-learn (>=0.24.0)
